sos_python/__init__.py
sos_python/_version.py
sos_python/kernel.py
sos_python-0.20.2.dist-info/LICENSE
sos_python-0.20.2.dist-info/METADATA
sos_python-0.20.2.dist-info/WHEEL
sos_python-0.20.2.dist-info/entry_points.txt
sos_python-0.20.2.dist-info/top_level.txt
sos_python-0.20.2.dist-info/RECORD
