Metadata-Version: 2.1
Name: sos-python
Version: 0.20.2
Summary: SoS Notebook extension for languages Python 2 and Python 3
Home-page: https://github.com/vatlab/SOS
Author: Bo Peng
Author-email: bo.peng@bcm.edu
Maintainer: Bo Peng
Maintainer-email: bo.peng@bcm.edu
License: 3-clause BSD
Classifier: Development Status :: 4 - Beta
Classifier: Environment :: Console
Classifier: License :: OSI Approved :: BSD License
Classifier: Natural Language :: English
Classifier: Operating System :: POSIX :: Linux
Classifier: Operating System :: MacOS :: MacOS X
Classifier: Operating System :: Microsoft :: Windows
Classifier: Intended Audience :: Information Technology
Classifier: Intended Audience :: Science/Research
Classifier: Programming Language :: Python :: 3 :: Only
Classifier: Programming Language :: Python :: Implementation :: CPython
License-File: LICENSE
Requires-Dist: sos >=0.19.8
Requires-Dist: sos-notebook >=0.24.0
